README.md
setup.cfg
setup.py
bin/__init__.py
bin/convert.py
bin/detect.py
bin/train.py
bin/visualize_dataset.py
bopflow/__init__.py
bopflow/const.py
bopflow/iomanage.py
bopflow.egg-info/PKG-INFO
bopflow.egg-info/SOURCES.txt
bopflow.egg-info/dependency_links.txt
bopflow.egg-info/requires.txt
bopflow.egg-info/top_level.txt
bopflow/models/__init__.py
bopflow/models/batch_norm.py
bopflow/models/darknet.py
bopflow/models/utils.py
bopflow/models/yolonet.py
bopflow/training/__init__.py
bopflow/training/transfer.py
bopflow/training/visualize.py
bopflow/transform/__init__.py
bopflow/transform/image.py
bopflow/transform/records.py